






{"id":"tag:search.twitter.com,2005:657244703788630016","objectType":"activity","actor":{"objectType":"person","id":"id:twitter.com:16958875","link":"http://www.twitter.com/Gnip","displayName":"Gnip, Inc.","postedTime":"2008-10-24T23:22:09.000Z","image":"https://pbs.twimg.com/profile_images/378800000713056041/16ea2bda3d29b422176b5996aee0ed00_normal.png","summary":"Gnip is the world's largest and most trusted provider of social data. Acquired by @Twitter in April 2014. HQ office is @TwitterBoulder.","links":[{"href":"http://gnip.com","rel":"me"}],"friendsCount":2133,"followersCount":25952,"listedCount":724,"statusesCount":2443,"twitterTimeZone":"Mountain Time (US & Canada)","verified":true,"utcOffset":"-21600","preferredUsername":"Gnip","languages":["en"],"location":{"objectType":"place","displayName":"Boulder, CO"},"favoritesCount":2354},"verb":"post","postedTime":"2015-10-22T17:18:43.000Z","generator":{"displayName":"Twitter Web Client","link":"http://twitter.com"},"provider":{"objectType":"service","displayName":"Twitter","link":"http://www.twitter.com"},"link":"http://twitter.com/Gnip/statuses/657244703788630016","body":"Thrilled to be partnering with @techstars to help early-stage companies build on Twitter data. https://t.co/dsJdv9op91","object":{"objectType":"note","id":"object:search.twitter.com,2005:657244703788630016","summary":"Thrilled to be partnering with @techstars to help early-stage companies build on Twitter data. https://t.co/dsJdv9op91","link":"http://twitter.com/Gnip/statuses/657244703788630016","postedTime":"2015-10-22T17:18:43.000Z"},"favoritesCount":0,"location":{"objectType":"place","displayName":"California, USA","name":"California","country_code":"United States","twitter_country_code":"US","link":"https://api.twitter.com/1.1/geo/id/fbd6d2f5a4e4a15e.json","geo":{"type":"Polygon","coordinates":[[[-124.482003,32.528832],[-124.482003,42.009519],[-114.131212,42.009519],[-114.131212,32.528832]]]},"twitter_place_type":"admin"},"twitter_entities":{"hashtags":[],"urls":[{"url":"https://t.co/dsJdv9op91","expanded_url":"http://www.techstars.com/techstars-twitter-partner-to-give-techstars-startups-access-to-twitter-data/","display_url":"techstars.com/techstars-twit…","indices":[95,118]}],"user_mentions":[{"screen_name":"techstars","name":"techstars","id":14277276,"id_str":"14277276","indices":[31,41]}],"symbols":[]},"twitter_filter_level":"low","twitter_lang":"en","retweetCount":0,"gnip":{"matching_rules":[{"value":"from:gnip","tag":null}],"urls":[{"url":"https://t.co/dsJdv9op91","expanded_url":"http://www.techstars.com/techstars-twitter-partner-to-give-techstars-startups-access-to-twitter-data/","expanded_status":200}],"klout_score":55,"klout_profile":{"topics":[{"klout_topic_id":"6231772432486389545","displayName":"Social Networks","link":"http://klout.com/topic/id/6231772432486389545"},{"klout_topic_id":"9186140909846789085","displayName":"Customer Service","link":"http://klout.com/topic/id/9186140909846789085"}],"klout_user_id":"651348","link":"http://klout.com/user/id/651348"},"language":{"value":"en"},"profileLocations":[{"objectType":"place","geo":{"type":"point","coordinates":[-105.27055,40.01499]},"address":{"country":"United States","countryCode":"US","locality":"Boulder","region":"Colorado","subRegion":"Boulder County"},"displayName":"Boulder, Colorado, United States"}]}}

{"info":{"message":"Replay Request Completed","sent":"2015-11-19T00:14:21+00:00","activity_count":1}}
