

{"id":"tag:search.twitter.com,2005:656951171639209985","objectType":"activity","actor":{"objectType":"person","id":"id:twitter.com:16958875","link":"http://www.twitter.com/Gnip","displayName":"Gnip, Inc.","postedTime":"2008-10-24T23:22:09.000Z","image":"https://pbs.twimg.com/profile_images/378800000713056041/16ea2bda3d29b422176b5996aee0ed00_normal.png","summary":"Gnip is the world's largest and most trusted provider of social data. Acquired by @Twitter in April 2014. HQ office is @TwitterBoulder.","links":[{"href":"http://gnip.com","rel":"me"}],"friendsCount":2133,"followersCount":25792,"listedCount":721,"statusesCount":2441,"twitterTimeZone":"Mountain Time (US & Canada)","verified":true,"utcOffset":"-21600","preferredUsername":"Gnip","languages":["en"],"location":{"objectType":"place","displayName":"Boulder, CO"},"favoritesCount":2354},"verb":"share","postedTime":"2015-10-21T21:52:19.000Z","generator":{"displayName":"Twitter Web Client","link":"http://twitter.com"},"provider":{"objectType":"service","displayName":"Twitter","link":"http://www.twitter.com"},"link":"http://twitter.com/Gnip/statuses/656951171639209985","body":"RT @Flight: .@robjohnson dives into how we built GNIP's newest APIs- for Engagements, Audience Insights, and Full Archive Search https://t.…","object":{"id":"tag:search.twitter.com,2005:656946159185858560","objectType":"activity","actor":{"objectType":"person","id":"id:twitter.com:2549012761","link":"http://www.twitter.com/Flight","displayName":"Twitter Flight","postedTime":"2014-06-06T01:28:59.000Z","image":"https://pbs.twimg.com/profile_images/509742189727866880/L_7Co2EV_normal.png","summary":"Find out what we’re building to help take your apps & businesses to the next level! Tune in live 10.21.2015: http://twitterflight.com #TwitterFlight","links":[{"href":"http://www.twitterflight.com","rel":"me"}],"friendsCount":5,"followersCount":50884,"listedCount":263,"statusesCount":531,"twitterTimeZone":"Arizona","verified":true,"utcOffset":"-25200","preferredUsername":"Flight","languages":["en"],"location":{"objectType":"place","displayName":"San Francisco, CA"},"favoritesCount":278},"verb":"post","postedTime":"2015-10-21T21:32:24.000Z","generator":{"displayName":"Twitter Web Client","link":"http://twitter.com"},"provider":{"objectType":"service","displayName":"Twitter","link":"http://www.twitter.com"},"link":"http://twitter.com/Flight/statuses/656946159185858560","body":".@robjohnson dives into how we built GNIP's newest APIs- for Engagements, Audience Insights, and Full Archive Search https://t.co/wiAdtKva51","object":{"objectType":"note","id":"object:search.twitter.com,2005:656946159185858560","summary":".@robjohnson dives into how we built GNIP's newest APIs- for Engagements, Audience Insights, and Full Archive Search https://t.co/wiAdtKva51","link":"http://twitter.com/Flight/statuses/656946159185858560","postedTime":"2015-10-21T21:32:24.000Z"},"favoritesCount":6,"twitter_entities":{"hashtags":[],"urls":[],"user_mentions":[{"screen_name":"robjohnson","name":"Rob Johnson","id":6264412,"id_str":"6264412","indices":[1,12]}],"symbols":[],"media":[{"id":656946158644822016,"id_str":"656946158644822016","indices":[117,140],"media_url":"http://pbs.twimg.com/media/CR3xDPaVAAA9o0I.jpg","media_url_https":"https://pbs.twimg.com/media/CR3xDPaVAAA9o0I.jpg","url":"https://t.co/wiAdtKva51","display_url":"pic.twitter.com/wiAdtKva51","expanded_url":"http://twitter.com/Flight/status/656946159185858560/photo/1","type":"photo","sizes":{"small":{"w":340,"h":255,"resize":"fit"},"large":{"w":877,"h":658,"resize":"fit"},"medium":{"w":600,"h":450,"resize":"fit"},"thumb":{"w":150,"h":150,"resize":"crop"}}}]},"twitter_extended_entities":{"media":[{"id":656946158644822016,"id_str":"656946158644822016","indices":[117,140],"media_url":"http://pbs.twimg.com/media/CR3xDPaVAAA9o0I.jpg","media_url_https":"https://pbs.twimg.com/media/CR3xDPaVAAA9o0I.jpg","url":"https://t.co/wiAdtKva51","display_url":"pic.twitter.com/wiAdtKva51","expanded_url":"http://twitter.com/Flight/status/656946159185858560/photo/1","type":"photo","sizes":{"small":{"w":340,"h":255,"resize":"fit"},"large":{"w":877,"h":658,"resize":"fit"},"medium":{"w":600,"h":450,"resize":"fit"},"thumb":{"w":150,"h":150,"resize":"crop"}}}]},"twitter_filter_level":"low","twitter_lang":"en"},"favoritesCount":0,"twitter_entities":{"hashtags":[],"urls":[],"user_mentions":[{"screen_name":"Flight","name":"Twitter Flight","id":2549012761,"id_str":"2549012761","indices":[3,10]},{"screen_name":"robjohnson","name":"Rob Johnson","id":6264412,"id_str":"6264412","indices":[13,24]}],"symbols":[],"media":[{"id":656946158644822016,"id_str":"656946158644822016","indices":[139,140],"media_url":"http://pbs.twimg.com/media/CR3xDPaVAAA9o0I.jpg","media_url_https":"https://pbs.twimg.com/media/CR3xDPaVAAA9o0I.jpg","url":"https://t.co/wiAdtKva51","display_url":"pic.twitter.com/wiAdtKva51","expanded_url":"http://twitter.com/Flight/status/656946159185858560/photo/1","type":"photo","sizes":{"small":{"w":340,"h":255,"resize":"fit"},"large":{"w":877,"h":658,"resize":"fit"},"medium":{"w":600,"h":450,"resize":"fit"},"thumb":{"w":150,"h":150,"resize":"crop"}},"source_status_id":656946159185858560,"source_status_id_str":"656946159185858560","source_user_id":2549012761,"source_user_id_str":"2549012761"}]},"twitter_extended_entities":{"media":[{"id":656946158644822016,"id_str":"656946158644822016","indices":[139,140],"media_url":"http://pbs.twimg.com/media/CR3xDPaVAAA9o0I.jpg","media_url_https":"https://pbs.twimg.com/media/CR3xDPaVAAA9o0I.jpg","url":"https://t.co/wiAdtKva51","display_url":"pic.twitter.com/wiAdtKva51","expanded_url":"http://twitter.com/Flight/status/656946159185858560/photo/1","type":"photo","sizes":{"small":{"w":340,"h":255,"resize":"fit"},"large":{"w":877,"h":658,"resize":"fit"},"medium":{"w":600,"h":450,"resize":"fit"},"thumb":{"w":150,"h":150,"resize":"crop"}},"source_status_id":656946159185858560,"source_status_id_str":"656946159185858560","source_user_id":2549012761,"source_user_id_str":"2549012761"}]},"twitter_filter_level":"low","twitter_lang":"en","retweetCount":2,"gnip":{"matching_rules":[{"value":"from:gnip","tag":null}],"urls":[{"url":"https://t.co/wiAdtKva51","expanded_url":"http://twitter.com/Flight/status/656946159185858560/photo/1","expanded_status":200}],"klout_score":55,"klout_profile":{"topics":[{"klout_topic_id":"6231772432486389545","displayName":"Social Networks","link":"http://klout.com/topic/id/6231772432486389545"},{"klout_topic_id":"9186140909846789085","displayName":"Customer Service","link":"http://klout.com/topic/id/9186140909846789085"}],"klout_user_id":"651348","link":"http://klout.com/user/id/651348"},"language":{"value":"en"},"profileLocations":[{"objectType":"place","geo":{"type":"point","coordinates":[-105.27055,40.01499]},"address":{"country":"United States","countryCode":"US","locality":"Boulder","region":"Colorado","subRegion":"Boulder County"},"displayName":"Boulder, Colorado, United States"}]}}




{"info":{"message":"Replay Request Completed","sent":"2015-11-19T00:12:44+00:00","activity_count":1}}
